LICENSE.txt
MANIFEST.in
NEWS.rst
README.rst
setup.py
setup_helpers.py
flufl/__init__.py
flufl.testing.egg-info/PKG-INFO
flufl.testing.egg-info/SOURCES.txt
flufl.testing.egg-info/dependency_links.txt
flufl.testing.egg-info/entry_points.txt
flufl.testing.egg-info/namespace_packages.txt
flufl.testing.egg-info/top_level.txt
flufl/testing/__init__.py
flufl/testing/imports.py
flufl/testing/nose.py