Metadata-Version: 1.1
Name: flufl.testing
Version: 0.6
Summary: A small collection of test tool plugins
Home-page: https://gitlab.com/warsaw/flufl.testing
Author: Barry Warsaw
Author-email: barry@python.org
License: ASLv2
Download-URL: https://pypi.python.org/pypi/flufl.testing
Platform: UNKNOWN
Classifier: Development Status :: 4 - Beta
Classifier: Environment :: Plugins
Classifier: Intended Audience :: Developers
Classifier: License :: OSI Approved :: Apache Software License
Classifier: Programming Language :: Python :: 3
